{
    "created_time": "2021-05-16T06:39:22Z",
    "files": [
        {
            "attachment_folder": "",
            "created_time": "2021-05-16T06:39:22Z",
            "id": "0",
            "modified_time": "2021-05-16T06:39:22Z",
            "name": "640 (1).jpg",
            "tags": [
            ]
        },
        {
            "attachment_folder": "",
            "created_time": "2021-05-16T06:39:22Z",
            "id": "0",
            "modified_time": "2021-05-16T06:39:22Z",
            "name": "640 (10).jpg",
            "tags": [
            ]
        },
        {
            "attachment_folder": "",
            "created_time": "2021-05-16T06:39:22Z",
            "id": "0",
            "modified_time": "2021-05-16T06:39:22Z",
            "name": "640 (11).jpg",
            "tags": [
            ]
        },
        {
            "attachment_folder": "",
            "created_time": "2021-05-16T06:39:22Z",
            "id": "0",
            "modified_time": "2021-05-16T06:39:22Z",
            "name": "640 (12).jpg",
            "tags": [
            ]
        },
        {
            "attachment_folder": "",
            "created_time": "2021-05-16T06:39:22Z",
            "id": "0",
            "modified_time": "2021-05-16T06:39:22Z",
            "name": "640 (13).jpg",
            "tags": [
            ]
        },
        {
            "attachment_folder": "",
            "created_time": "2021-05-16T06:39:22Z",
            "id": "0",
            "modified_time": "2021-05-16T06:39:22Z",
            "name": "640 (14).jpg",
            "tags": [
            ]
        },
        {
            "attachment_folder": "",
            "created_time": "2021-05-16T06:39:22Z",
            "id": "0",
            "modified_time": "2021-05-16T06:39:22Z",
            "name": "640 (2).jpg",
            "tags": [
            ]
        },
        {
            "attachment_folder": "",
            "created_time": "2021-05-16T06:39:22Z",
            "id": "0",
            "modified_time": "2021-05-16T06:39:22Z",
            "name": "640 (3).jpg",
            "tags": [
            ]
        },
        {
            "attachment_folder": "",
            "created_time": "2021-05-16T06:39:22Z",
            "id": "0",
            "modified_time": "2021-05-16T06:39:22Z",
            "name": "640 (4).jpg",
            "tags": [
            ]
        },
        {
            "attachment_folder": "",
            "created_time": "2021-05-16T06:39:22Z",
            "id": "0",
            "modified_time": "2021-05-16T06:39:22Z",
            "name": "640 (5).jpg",
            "tags": [
            ]
        },
        {
            "attachment_folder": "",
            "created_time": "2021-05-16T06:39:22Z",
            "id": "0",
            "modified_time": "2021-05-16T06:39:22Z",
            "name": "640 (6).jpg",
            "tags": [
            ]
        },
        {
            "attachment_folder": "",
            "created_time": "2021-05-16T06:39:22Z",
            "id": "0",
            "modified_time": "2021-05-16T06:39:22Z",
            "name": "640 (7).jpg",
            "tags": [
            ]
        },
        {
            "attachment_folder": "",
            "created_time": "2021-05-16T06:39:22Z",
            "id": "0",
            "modified_time": "2021-05-16T06:39:22Z",
            "name": "640 (8).jpg",
            "tags": [
            ]
        },
        {
            "attachment_folder": "",
            "created_time": "2021-05-16T06:39:22Z",
            "id": "0",
            "modified_time": "2021-05-16T06:39:22Z",
            "name": "640 (9).jpg",
            "tags": [
            ]
        },
        {
            "attachment_folder": "",
            "created_time": "2021-05-16T06:39:22Z",
            "id": "0",
            "modified_time": "2021-05-16T06:39:22Z",
            "name": "640.jpg",
            "tags": [
            ]
        }
    ],
    "folders": [
    ],
    "id": "0",
    "modified_time": "2021-05-16T06:39:22Z",
    "version": "1"
}
